nurmonic/__init__.py
nurmonic/nurmonic.py
nurmonic-0.3.0.dist-info/METADATA
nurmonic-0.3.0.dist-info/WHEEL
nurmonic-0.3.0.dist-info/top_level.txt
nurmonic-0.3.0.dist-info/RECORD
