Metadata-Version: 2.1
Name: nurmonic
Version: 0.3.0
Summary: A Python client for the Nurmonic API.
Home-page: https://nurmonic.xyz
Author: Reksely
Author-email: reksely@gmail.com
Requires-Dist: requests >=2.25.1
